[{"fillings":["Klawf Stick","Red Bell Pepper"],"condiments":["Curry Powder"],"mealPowers":[{"power":"Humungo Power","type":"Fire","level":1},{"power":"Encounter Power","type":"Bug","level":1},{"power":"Catching Power","type":"Ice","level":1}]},{"fillings":["Cheese","Red Bell Pepper"],"condiments":["Jam","Ketchup","Spicy Herba Mystica"],"mealPowers":[{"power":"Title Power","type":"Fire","level":2},{"power":"Humungo Power","type":"Fire","level":2},{"power":"Catching Power","type":"Ice","level":2}]},{"fillings":["Noodles","Rice","Basil"],"condiments":["Jam","Jam","Pepper","Sour Herba Mystica"],"mealPowers":[{"power":"Title Power","type":"Ice","level":2},{"power":"Catching Power","type":"Ice","level":2},{"power":"Humungo Power","type":"Fire","level":2}]},{"fillings":["Noodles","Rice","Basil"],"condiments":["Jam","Jam","Pepper","Sweet Herba Mystica"],"mealPowers":[{"power":"Title Power","type":"Ice","level":2},{"power":"Catching Power","type":"Ice","level":2},{"power":"Humungo Power","type":"Fire","level":2}]},{"fillings":["Noodles","Noodles","Potato Salad","Rice","Rice"],"condiments":["Jam","Curry Powder","Peanut Butter","Sour Herba Mystica"],"mealPowers":[{"power":"Title Power","type":"Fire","level":2},{"power":"Humungo Power","type":"Fire","level":2},{"power":"Catching Power","type":"Ice","level":2}]},{"fillings":["Fried Fillet","Fried Fillet","Potato Tortilla","Potato Tortilla","Klawf Stick"],"condiments":["Curry Powder","Curry Powder","Olive Oil","Spicy Herba Mystica"],"mealPowers":[{"power":"Title Power","type":"Ice","level":2},{"power":"Catching Power","type":"Ice","level":2},{"power":"Humungo Power","type":"Fire","level":2}]},{"fillings":["Noodles","Noodles","Potato Salad","Rice","Rice"],"condiments":["Olive Oil","Pepper","Yogurt","Sweet Herba Mystica"],"mealPowers":[{"power":"Title Power","type":"Fire","level":2},{"power":"Humungo Power","type":"Fire","level":2},{"power":"Catching Power","type":"Ice","level":2}]}]