[{"fillings":["Avocado"],"condiments":["Butter","Cream Cheese","Marmalade"],"mealPowers":[{"power":"Catching Power","type":"Dragon","level":1},{"power":"Item Drop Power","type":"Fighting","level":1},{"power":"Encounter Power","type":"Bug","level":1}]},{"fillings":["Banana","Banana","Strawberry","Strawberry"],"condiments":["Marmalade","Marmalade","Salty Herba Mystica"],"mealPowers":[{"power":"Title Power","type":"Fighting","level":2},{"power":"Item Drop Power","type":"Fighting","level":2},{"power":"Encounter Power","type":"Bug","level":2}]},{"fillings":["Hamburger","Rice","Cherry Tomatoes","Cherry Tomatoes"],"condiments":["Curry Powder","Horseradish","Horseradish","Bitter Herba Mystica"],"mealPowers":[{"power":"Title Power","type":"Bug","level":2},{"power":"Encounter Power","type":"Bug","level":2},{"power":"Item Drop Power","type":"Fighting","level":2}]},{"fillings":["Banana","Banana","Strawberry","Strawberry"],"condiments":["Cream Cheese","Cream Cheese","Horseradish","Salty Herba Mystica"],"mealPowers":[{"power":"Title Power","type":"Bug","level":2},{"power":"Encounter Power","type":"Bug","level":2},{"power":"Item Drop Power","type":"Fighting","level":2}]},{"fillings":["Hamburger","Hamburger","Cherry Tomatoes","Cherry Tomatoes","Herbed Sausage"],"condiments":["Horseradish","Marmalade","Bitter Herba Mystica"],"mealPowers":[{"power":"Title Power","type":"Fighting","level":2},{"power":"Item Drop Power","type":"Fighting","level":2},{"power":"Encounter Power","type":"Bug","level":2}]},{"fillings":["Smoked Fillet"],"condiments":["Butter","Cream Cheese","Marmalade","Bitter Herba Mystica"],"mealPowers":[{"power":"Title Power","type":"Dark","level":2},{"power":"Item Drop Power","type":"Fighting","level":2},{"power":"Encounter Power","type":"Bug","level":1}]},{"fillings":["Banana","Strawberry"],"condiments":["Salty Herba Mystica"],"mealPowers":[{"power":"Title Power","type":"Normal","level":2},{"power":"Encounter Power","type":"Bug","level":2},{"power":"Item Drop Power","type":"Fighting","level":1}]},{"fillings":["Hamburger","Cherry Tomatoes","Kiwi","Pickle"],"condiments":["Cream Cheese","Marmalade","Marmalade","Sour Herba Mystica"],"mealPowers":[{"power":"Title Power","type":"Poison","level":2},{"power":"Encounter Power","type":"Bug","level":2},{"power":"Item Drop Power","type":"Fighting","level":1}]},{"fillings":["Hamburger","Avocado","Jalape&ntilde;o","Banana","Strawberry"],"condiments":["Curry Powder","Mayonnaise","Wasabi","Spicy Herba Mystica"],"mealPowers":[{"power":"Title Power","type":"Normal","level":2},{"power":"Encounter Power","type":"Bug","level":2},{"power":"Item Drop Power","type":"Fighting","level":1}]}]