[{"fillings":["Onion"],"condiments":["Chili Sauce"],"mealPowers":[{"power":"Raid Power","type":"Psychic","level":1},{"power":"Encounter Power","type":"Grass","level":1},{"power":"Catching Power","type":"Water","level":1}]},{"fillings":["Potato Tortilla","Cherry Tomatoes","Cherry Tomatoes","Lettuce","Onion"],"condiments":["Curry Powder","Horseradish","Spicy Herba Mystica"],"mealPowers":[{"power":"Title Power","type":"Grass","level":2},{"power":"Encounter Power","type":"Grass","level":2},{"power":"Raid Power","type":"Psychic","level":2}]},{"fillings":["Hamburger","Rice","Avocado","Onion","Onion"],"condiments":["Chili Sauce","Curry Powder","Spicy Herba Mystica"],"mealPowers":[{"power":"Title Power","type":"Psychic","level":2},{"power":"Raid Power","type":"Psychic","level":2},{"power":"Encounter Power","type":"Grass","level":2}]},{"fillings":["Hamburger","Hamburger","Potato Tortilla","Lettuce","Onion"],"condiments":["Curry Powder","Curry Powder","Sweet Herba Mystica"],"mealPowers":[{"power":"Title Power","type":"Grass","level":2},{"power":"Encounter Power","type":"Grass","level":2},{"power":"Raid Power","type":"Psychic","level":2}]},{"fillings":["Hamburger","Rice","Avocado","Onion","Onion"],"condiments":["Chili Sauce","Curry Powder","Sweet Herba Mystica"],"mealPowers":[{"power":"Title Power","type":"Psychic","level":2},{"power":"Raid Power","type":"Psychic","level":2},{"power":"Encounter Power","type":"Grass","level":2}]},{"fillings":["Potato Tortilla","Potato Tortilla","Potato Tortilla","Potato Tortilla","Lettuce"],"condiments":["Butter","Butter","Salt","Salty Herba Mystica"],"mealPowers":[{"power":"Title Power","type":"Grass","level":2},{"power":"Encounter Power","type":"Grass","level":2},{"power":"Raid Power","type":"Psychic","level":2}]},{"fillings":["Hamburger","Potato Tortilla","Potato Tortilla","Potato Tortilla","Basil"],"condiments":["Ketchup","Mayonnaise","Salt","Salty Herba Mystica"],"mealPowers":[{"power":"Title Power","type":"Psychic","level":2},{"power":"Raid Power","type":"Psychic","level":2},{"power":"Encounter Power","type":"Grass","level":2}]},{"fillings":["Cucumber"],"condiments":["Chili Sauce","Curry Powder","Vinegar","Sweet Herba Mystica"],"mealPowers":[{"power":"Title Power","type":"Water","level":2},{"power":"Raid Power","type":"Psychic","level":2},{"power":"Encounter Power","type":"Grass","level":1}]},{"fillings":["Onion","Onion"],"condiments":["Chili Sauce","Spicy Herba Mystica"],"mealPowers":[{"power":"Title Power","type":"Psychic","level":2},{"power":"Raid Power","type":"Psychic","level":2},{"power":"Encounter Power","type":"Grass","level":1}]},{"fillings":["Potato Tortilla","Lettuce"],"condiments":["Butter","Salt","Salty Herba Mystica"],"mealPowers":[{"power":"Title Power","type":"Grass","level":2},{"power":"Encounter Power","type":"Grass","level":2},{"power":"Raid Power","type":"Psychic","level":1}]}]