[{"fillings":["Rice","Rice","Rice","Rice","Rice","Rice"],"condiments":["Butter","Chili Sauce","Horseradish","Marmalade"],"mealPowers":[{"power":"Raid Power","type":"Fighting","level":2},{"power":"Humungo Power","type":"Flying","level":2},{"power":"Encounter Power","type":"Normal","level":1}]},{"fillings":["Rice"],"condiments":["Mayonnaise","Whipped Cream"],"mealPowers":[{"power":"Catching Power","type":"Normal","level":1},{"power":"Raid Power","type":"Fighting","level":1},{"power":"Humungo Power","type":"Flying","level":1}]},{"fillings":["Rice"],"condiments":["Ketchup","Spicy Herba Mystica"],"mealPowers":[{"power":"Title Power","type":"Flying","level":2},{"power":"Humungo Power","type":"Flying","level":2},{"power":"Raid Power","type":"Fighting","level":2}]},{"fillings":["Rice"],"condiments":["Butter","Marmalade","Spicy Herba Mystica"],"mealPowers":[{"power":"Title Power","type":"Fighting","level":2},{"power":"Raid Power","type":"Fighting","level":2},{"power":"Humungo Power","type":"Flying","level":2}]},{"fillings":["Rice","Rice"],"condiments":["Chili Sauce","Horseradish","Marmalade","Sweet Herba Mystica"],"mealPowers":[{"power":"Title Power","type":"Fighting","level":2},{"power":"Raid Power","type":"Fighting","level":2},{"power":"Humungo Power","type":"Flying","level":2}]},{"fillings":["Rice","Rice","Rice","Rice","Rice","Prosciutto"],"condiments":["Horseradish","Sweet Herba Mystica"],"mealPowers":[{"power":"Title Power","type":"Flying","level":2},{"power":"Humungo Power","type":"Flying","level":2},{"power":"Raid Power","type":"Fighting","level":2}]}]