[{"fillings":["Green Bell Pepper"],"condiments":["Cream Cheese","Spicy Herba Mystica"],"mealPowers":[{"power":"Title Power","type":"Poison","level":2},{"power":"Raid Power","type":"Steel","level":2},{"power":"Encounter Power","type":"Bug","level":1}]},{"fillings":["Green Bell Pepper"],"condiments":["Cream Cheese","Curry Powder","Sweet Herba Mystica"],"mealPowers":[{"power":"Title Power","type":"Poison","level":2},{"power":"Raid Power","type":"Steel","level":2},{"power":"Encounter Power","type":"Bug","level":1}]},{"fillings":["Cheese","Green Bell Pepper"],"condiments":["Ketchup","Peanut Butter","Bitter Herba Mystica"],"mealPowers":[{"power":"Title Power","type":"Poison","level":2},{"power":"Exp. Point Power","type":"Poison","level":2},{"power":"Raid Power","type":"Steel","level":2}]},{"fillings":["Cheese","Green Bell Pepper"],"condiments":["Ketchup","Peanut Butter","Salty Herba Mystica"],"mealPowers":[{"power":"Title Power","type":"Poison","level":2},{"power":"Encounter Power","type":"Poison","level":2},{"power":"Raid Power","type":"Steel","level":2}]},{"fillings":["Cheese","Green Bell Pepper"],"condiments":["Ketchup","Peanut Butter","Sour Herba Mystica"],"mealPowers":[{"power":"Title Power","type":"Poison","level":2},{"power":"Teensy Power","type":"Poison","level":2},{"power":"Raid Power","type":"Steel","level":2}]},{"fillings":["Cheese","Green Bell Pepper"],"condiments":["Ketchup","Peanut Butter","Spicy Herba Mystica"],"mealPowers":[{"power":"Title Power","type":"Poison","level":2},{"power":"Humungo Power","type":"Poison","level":2},{"power":"Raid Power","type":"Steel","level":2}]},{"fillings":["Cheese","Green Bell Pepper"],"condiments":["Ketchup","Peanut Butter","Sweet Herba Mystica"],"mealPowers":[{"power":"Title Power","type":"Poison","level":2},{"power":"Egg Power","level":2},{"power":"Raid Power","type":"Steel","level":2}]},{"fillings":["Cheese","Green Bell Pepper"],"condiments":["Cream Cheese","Ketchup","Mayonnaise","Sweet Herba Mystica"],"mealPowers":[{"power":"Title Power","type":"Poison","level":2},{"power":"Catching Power","type":"Poison","level":2},{"power":"Raid Power","type":"Steel","level":2}]},{"fillings":["Fried Fillet","Kiwi","Watercress","Watercress"],"condiments":["Chili Sauce","Ketchup","Peanut Butter","Salty Herba Mystica"],"mealPowers":[{"power":"Title Power","type":"Poison","level":2},{"power":"Raid Power","type":"Steel","level":2},{"power":"Encounter Power","type":"Flying","level":1}]},{"fillings":["Green Bell Pepper"],"condiments":["Peanut Butter","Salty Herba Mystica"],"mealPowers":[{"power":"Title Power","type":"Poison","level":2},{"power":"Encounter Power","type":"Fire","level":2},{"power":"Raid Power","type":"Steel","level":1}]},{"fillings":["Green Bell Pepper"],"condiments":["Peanut Butter","Salt","Bitter Herba Mystica"],"mealPowers":[{"power":"Title Power","type":"Poison","level":2},{"power":"Exp. Point Power","type":"Fire","level":2},{"power":"Raid Power","type":"Steel","level":1}]},{"fillings":["Green Bell Pepper"],"condiments":["Chili Sauce","Peanut Butter","Sour Herba Mystica"],"mealPowers":[{"power":"Title Power","type":"Poison","level":2},{"power":"Catching Power","type":"Fire","level":2},{"power":"Raid Power","type":"Steel","level":1}]}]