[{"fillings":["Green Bell Pepper"],"condiments":["Chili Sauce","Cream Cheese","Peanut Butter","Spicy Herba Mystica"],"mealPowers":[{"power":"Title Power","type":"Poison","level":2},{"power":"Raid Power","type":"Water","level":2},{"power":"Exp. Point Power","type":"Steel","level":1}]},{"fillings":["Green Bell Pepper"],"condiments":["Chili Sauce","Ketchup","Wasabi","Sweet Herba Mystica"],"mealPowers":[{"power":"Title Power","type":"Poison","level":2},{"power":"Raid Power","type":"Water","level":2},{"power":"Encounter Power","type":"Flying","level":1}]},{"fillings":["Potato Tortilla","Pineapple","Basil","Watercress"],"condiments":["Ketchup","Ketchup","Pepper","Salty Herba Mystica"],"mealPowers":[{"power":"Title Power","type":"Poison","level":2},{"power":"Raid Power","type":"Water","level":2},{"power":"Encounter Power","type":"Dragon","level":1}]},{"fillings":["Potato Tortilla","Lettuce","Cucumber","Cucumber","Green Bell Pepper"],"condiments":["Curry Powder","Horseradish","Sweet Herba Mystica"],"mealPowers":[{"power":"Title Power","type":"Poison","level":2},{"power":"Encounter Power","type":"Poison","level":2},{"power":"Raid Power","type":"Water","level":2}]},{"fillings":["Fried Fillet","Potato Tortilla","Green Bell Pepper","Basil","Basil"],"condiments":["Butter","Chili Sauce","Peanut Butter","Bitter Herba Mystica"],"mealPowers":[{"power":"Title Power","type":"Poison","level":2},{"power":"Exp. Point Power","type":"Poison","level":2},{"power":"Raid Power","type":"Water","level":2}]},{"fillings":["Fried Fillet","Fried Fillet","Potato Tortilla","Potato Tortilla","Green Bell Pepper"],"condiments":["Chili Sauce","Ketchup","Ketchup","Salty Herba Mystica"],"mealPowers":[{"power":"Title Power","type":"Poison","level":2},{"power":"Encounter Power","type":"Poison","level":2},{"power":"Raid Power","type":"Water","level":2}]},{"fillings":["Fried Fillet","Fried Fillet","Potato Tortilla","Potato Tortilla","Green Bell Pepper"],"condiments":["Chili Sauce","Ketchup","Yogurt","Sour Herba Mystica"],"mealPowers":[{"power":"Title Power","type":"Poison","level":2},{"power":"Catching Power","type":"Poison","level":2},{"power":"Raid Power","type":"Water","level":2}]},{"fillings":["Fried Fillet","Potato Tortilla","Basil","Basil","Watercress"],"condiments":["Butter","Ketchup","Marmalade","Sour Herba Mystica"],"mealPowers":[{"power":"Title Power","type":"Poison","level":2},{"power":"Raid Power","type":"Water","level":2},{"power":"Teensy Power","type":"Fire","level":1}]},{"fillings":["Hamburger","Rice","Klawf Stick","Green Bell Pepper","Green Bell Pepper"],"condiments":["Curry Powder","Peanut Butter","Wasabi","Spicy Herba Mystica"],"mealPowers":[{"power":"Title Power","type":"Poison","level":2},{"power":"Encounter Power","type":"Poison","level":2},{"power":"Raid Power","type":"Water","level":2}]},{"fillings":["Fried Fillet","Potato Tortilla","Green Bell Pepper","Basil","Basil"],"condiments":["Butter","Chili Sauce","Peanut Butter","Sweet Herba Mystica"],"mealPowers":[{"power":"Title Power","type":"Poison","level":2},{"power":"Egg Power","level":2},{"power":"Raid Power","type":"Water","level":2}]},{"fillings":["Green Bell Pepper"],"condiments":["Chili Sauce","Salty Herba Mystica"],"mealPowers":[{"power":"Title Power","type":"Poison","level":2},{"power":"Encounter Power","type":"Grass","level":2},{"power":"Raid Power","type":"Water","level":1}]},{"fillings":["Green Bell Pepper"],"condiments":["Chili Sauce","Salt","Bitter Herba Mystica"],"mealPowers":[{"power":"Title Power","type":"Poison","level":2},{"power":"Exp. Point Power","type":"Grass","level":2},{"power":"Raid Power","type":"Water","level":1}]},{"fillings":["Green Bell Pepper"],"condiments":["Chili Sauce","Yogurt","Sour Herba Mystica"],"mealPowers":[{"power":"Title Power","type":"Poison","level":2},{"power":"Catching Power","type":"Grass","level":2},{"power":"Raid Power","type":"Water","level":1}]}]