[{"fillings":["Noodles","Rice"],"condiments":["Jam","Ketchup","Sour Herba Mystica"],"mealPowers":[{"power":"Title Power","type":"Electric","level":2},{"power":"Catching Power","type":"Electric","level":2},{"power":"Humungo Power","type":"Flying","level":2}]},{"fillings":["Noodles","Rice"],"condiments":["Jam","Ketchup","Sweet Herba Mystica"],"mealPowers":[{"power":"Title Power","type":"Electric","level":2},{"power":"Catching Power","type":"Electric","level":2},{"power":"Humungo Power","type":"Flying","level":2}]},{"fillings":["Fried Fillet","Fried Fillet","Fried Fillet","Potato Tortilla","Potato Tortilla"],"condiments":["Salt","Spicy Herba Mystica"],"mealPowers":[{"power":"Title Power","type":"Electric","level":2},{"power":"Catching Power","type":"Electric","level":2},{"power":"Humungo Power","type":"Flying","level":2}]}]