[{"fillings":["Herbed Sausage","Apple"],"condiments":["Horseradish","Horseradish","Yogurt","Sour Herba Mystica"],"mealPowers":[{"power":"Title Power","type":"Fighting","level":2},{"power":"Catching Power","type":"Fighting","level":2},{"power":"Teensy Power","type":"Dark","level":2}]},{"fillings":["Potato Tortilla","Pineapple","Pickle"],"condiments":["Curry Powder","Mayonnaise","Wasabi","Sweet Herba Mystica"],"mealPowers":[{"power":"Title Power","type":"Fighting","level":2},{"power":"Catching Power","type":"Fighting","level":2},{"power":"Teensy Power","type":"Dark","level":2}]}]