[{"fillings":["Fried Fillet","Tomato"],"condiments":["Chili Sauce","Ketchup","Vinegar","Sweet Herba Mystica"],"mealPowers":[{"power":"Title Power","type":"Flying","level":2},{"power":"Catching Power","type":"Fairy","level":2},{"power":"Raid Power","type":"Water","level":1}]},{"fillings":["Prosciutto","Cucumber","Watercress"],"condiments":["Butter","Vinegar","Yogurt","Sour Herba Mystica"],"mealPowers":[{"power":"Title Power","type":"Flying","level":2},{"power":"Catching Power","type":"Fairy","level":2},{"power":"Raid Power","type":"Water","level":1}]}]