[{"fillings":["Yellow Bell Pepper","Tomato"],"condiments":["Butter","Salty Herba Mystica"],"mealPowers":[{"power":"Title Power","type":"Electric","level":2},{"power":"Encounter Power","type":"Bug","level":2},{"power":"Catching Power","type":"Fairy","level":1}]},{"fillings":["Cherry Tomatoes","Yellow Bell Pepper"],"condiments":["Vinegar","Wasabi","Yogurt","Sour Herba Mystica"],"mealPowers":[{"power":"Title Power","type":"Electric","level":2},{"power":"Catching Power","type":"Fairy","level":2},{"power":"Encounter Power","type":"Bug","level":1}]},{"fillings":["Cherry Tomatoes","Yellow Bell Pepper"],"condiments":["Vinegar","Wasabi","Yogurt","Sweet Herba Mystica"],"mealPowers":[{"power":"Title Power","type":"Electric","level":2},{"power":"Catching Power","type":"Fairy","level":2},{"power":"Encounter Power","type":"Bug","level":1}]},{"fillings":["Hamburger","Cherry Tomatoes","Red Onion","Yellow Bell Pepper","Tomato","Basil"],"condiments":["Jam","Marmalade","Marmalade","Sour Herba Mystica"],"mealPowers":[{"power":"Title Power","type":"Electric","level":2},{"power":"Encounter Power","type":"Bug","level":2},{"power":"Catching Power","type":"Fairy","level":1}]}]