[{"fillings":["Potato Tortilla","Apple","Cucumber","Ham","Watercress"],"condiments":["Cream Cheese","Bitter Herba Mystica"],"mealPowers":[{"power":"Title Power","type":"Steel","level":2},{"power":"Exp. Point Power","type":"Fighting","level":2},{"power":"Catching Power","type":"Flying","level":1}]},{"fillings":["Potato Tortilla","Apple","Yellow Bell Pepper","Smoked Fillet","Watercress"],"condiments":["Cream Cheese","Salty Herba Mystica"],"mealPowers":[{"power":"Title Power","type":"Steel","level":2},{"power":"Exp. Point Power","type":"Fighting","level":2},{"power":"Catching Power","type":"Flying","level":1}]}]