[{"fillings":["Fried Fillet","Potato Tortilla"],"condiments":["Chili Sauce","Sweet Herba Mystica"],"mealPowers":[{"power":"Title Power","type":"Water","level":2},{"power":"Raid Power","type":"Normal","level":2},{"power":"Catching Power","type":"Grass","level":1}]},{"fillings":["Cucumber","Tofu"],"condiments":["Chili Sauce","Chili Sauce","Peanut Butter","Sour Herba Mystica"],"mealPowers":[{"power":"Title Power","type":"Water","level":2},{"power":"Catching Power","type":"Grass","level":2},{"power":"Raid Power","type":"Normal","level":1}]},{"fillings":["Cucumber","Basil"],"condiments":["Chili Sauce","Mayonnaise","Whipped Cream","Sweet Herba Mystica"],"mealPowers":[{"power":"Title Power","type":"Water","level":2},{"power":"Catching Power","type":"Grass","level":2},{"power":"Raid Power","type":"Normal","level":1}]},{"fillings":["Fried Fillet","Lettuce"],"condiments":["Chili Sauce","Chili Sauce","Marmalade","Spicy Herba Mystica"],"mealPowers":[{"power":"Title Power","type":"Water","level":2},{"power":"Raid Power","type":"Normal","level":2},{"power":"Catching Power","type":"Grass","level":1}]}]