[{"fillings":["Fried Fillet","Lettuce","Green Bell Pepper"],"condiments":["Marmalade","Olive Oil","Pepper","Salty Herba Mystica"],"mealPowers":[{"power":"Title Power","type":"Poison","level":2},{"power":"Exp. Point Power","type":"Ice","level":2},{"power":"Catching Power","type":"Grass","level":1}]},{"fillings":["Potato Tortilla","Apple","Cucumber","Ham","Smoked Fillet","Basil"],"condiments":["Chili Sauce","Ketchup","Marmalade","Bitter Herba Mystica"],"mealPowers":[{"power":"Title Power","type":"Poison","level":2},{"power":"Exp. Point Power","type":"Ice","level":2},{"power":"Catching Power","type":"Grass","level":1}]}]