[{"fillings":["Klawf Stick","Onion"],"condiments":["Salty Herba Mystica"],"mealPowers":[{"power":"Title Power","type":"Psychic","level":2},{"power":"Encounter Power","type":"Normal","level":2},{"power":"Catching Power","type":"Ice","level":1}]},{"fillings":["Onion","Tofu"],"condiments":["Jam","Pepper","Vinegar","Sour Herba Mystica"],"mealPowers":[{"power":"Title Power","type":"Psychic","level":2},{"power":"Catching Power","type":"Ice","level":2},{"power":"Encounter Power","type":"Normal","level":1}]},{"fillings":["Onion","Tofu"],"condiments":["Jam","Pepper","Vinegar","Sweet Herba Mystica"],"mealPowers":[{"power":"Title Power","type":"Psychic","level":2},{"power":"Catching Power","type":"Ice","level":2},{"power":"Encounter Power","type":"Normal","level":1}]},{"fillings":["Hamburger","Klawf Stick","Bacon","Ham","Onion","Tofu"],"condiments":["Jam","Chili Sauce","Vinegar","Sour Herba Mystica"],"mealPowers":[{"power":"Title Power","type":"Psychic","level":2},{"power":"Encounter Power","type":"Normal","level":2},{"power":"Catching Power","type":"Ice","level":1}]}]