[{"fillings":["Noodles","Rice","Rice","Rice","Rice"],"condiments":["Ketchup","Peanut Butter","Sour Herba Mystica"],"mealPowers":[{"power":"Title Power","type":"Flying","level":2},{"power":"Humungo Power","type":"Flying","level":2},{"power":"Catching Power","type":"Normal","level":2}]},{"fillings":["Noodles","Noodles","Potato Salad","Rice","Rice"],"condiments":["Ketchup","Yogurt","Sweet Herba Mystica"],"mealPowers":[{"power":"Title Power","type":"Flying","level":2},{"power":"Humungo Power","type":"Flying","level":2},{"power":"Catching Power","type":"Normal","level":2}]},{"fillings":["Fried Fillet","Fried Fillet","Fried Fillet","Rice","Potato Tortilla","Potato Tortilla"],"condiments":["Chili Sauce","Ketchup","Spicy Herba Mystica"],"mealPowers":[{"power":"Title Power","type":"Flying","level":2},{"power":"Humungo Power","type":"Flying","level":2},{"power":"Catching Power","type":"Normal","level":2}]},{"fillings":["Prosciutto","Cheese"],"condiments":["Ketchup","Spicy Herba Mystica"],"mealPowers":[{"power":"Title Power","type":"Flying","level":2},{"power":"Humungo Power","type":"Flying","level":2},{"power":"Catching Power","type":"Normal","level":1}]}]