[{"fillings":["Fried Fillet","Fried Fillet","Potato Tortilla","Potato Tortilla","Cheese","Ham"],"condiments":["Wasabi","Sour Herba Mystica"],"mealPowers":[{"power":"Title Power","type":"Ground","level":2},{"power":"Teensy Power","type":"Ground","level":2},{"power":"Catching Power","type":"Psychic","level":2}]},{"fillings":["Cheese","Ham"],"condiments":["Salt","Sour Herba Mystica"],"mealPowers":[{"power":"Title Power","type":"Ground","level":2},{"power":"Teensy Power","type":"Ground","level":2},{"power":"Catching Power","type":"Psychic","level":1}]}]