[{"fillings":["Red Bell Pepper","Tofu"],"condiments":["Cream Cheese","Horseradish","Peanut Butter","Sour Herba Mystica"],"mealPowers":[{"power":"Title Power","type":"Normal","level":2},{"power":"Catching Power","type":"Steel","level":2},{"power":"Encounter Power","type":"Fire","level":1}]},{"fillings":["Red Bell Pepper","Tofu"],"condiments":["Cream Cheese","Mayonnaise","Peanut Butter","Sweet Herba Mystica"],"mealPowers":[{"power":"Title Power","type":"Normal","level":2},{"power":"Catching Power","type":"Steel","level":2},{"power":"Encounter Power","type":"Fire","level":1}]},{"fillings":["Hamburger","Tofu"],"condiments":["Horseradish","Olive Oil","Peanut Butter","Salty Herba Mystica"],"mealPowers":[{"power":"Title Power","type":"Normal","level":2},{"power":"Encounter Power","type":"Fire","level":2},{"power":"Catching Power","type":"Steel","level":1}]},{"fillings":["Hamburger","Lettuce","Cucumber","Red Bell Pepper","Tofu"],"condiments":["Jam","Marmalade","Marmalade","Sour Herba Mystica"],"mealPowers":[{"power":"Title Power","type":"Normal","level":2},{"power":"Encounter Power","type":"Fire","level":2},{"power":"Catching Power","type":"Steel","level":1}]}]