[{"fillings":["Cherry Tomatoes","Tomato"],"condiments":["Butter","Chili Sauce","Chili Sauce","Sour Herba Mystica"],"mealPowers":[{"power":"Title Power","type":"Bug","level":2},{"power":"Catching Power","type":"Water","level":2},{"power":"Raid Power","type":"Fairy","level":1}]},{"fillings":["Cherry Tomatoes","Tomato"],"condiments":["Butter","Chili Sauce","Chili Sauce","Sweet Herba Mystica"],"mealPowers":[{"power":"Title Power","type":"Bug","level":2},{"power":"Catching Power","type":"Water","level":2},{"power":"Raid Power","type":"Fairy","level":1}]},{"fillings":["Potato Tortilla","Cherry Tomatoes","Cucumber"],"condiments":["Cream Cheese","Whipped Cream","Yogurt","Spicy Herba Mystica"],"mealPowers":[{"power":"Title Power","type":"Bug","level":2},{"power":"Raid Power","type":"Fairy","level":2},{"power":"Catching Power","type":"Water","level":1}]}]