[{"fillings":["Avocado","Red Bell Pepper"],"condiments":["Butter","Chili Sauce","Chili Sauce","Sour Herba Mystica"],"mealPowers":[{"power":"Title Power","type":"Fire","level":2},{"power":"Catching Power","type":"Water","level":2},{"power":"Raid Power","type":"Dragon","level":1}]},{"fillings":["Avocado","Red Bell Pepper"],"condiments":["Chili Sauce","Chili Sauce","Mayonnaise","Sweet Herba Mystica"],"mealPowers":[{"power":"Title Power","type":"Fire","level":2},{"power":"Catching Power","type":"Water","level":2},{"power":"Raid Power","type":"Dragon","level":1}]},{"fillings":["Potato Tortilla","Cucumber","Yellow Bell Pepper"],"condiments":["Cream Cheese","Peanut Butter","Pepper","Spicy Herba Mystica"],"mealPowers":[{"power":"Title Power","type":"Fire","level":2},{"power":"Raid Power","type":"Dragon","level":2},{"power":"Catching Power","type":"Water","level":1}]},{"fillings":["Fried Fillet","Kiwi","Onion","Basil"],"condiments":["Curry Powder","Sweet Herba Mystica"],"mealPowers":[{"power":"Title Power","type":"Fire","level":2},{"power":"Raid Power","type":"Dragon","level":2},{"power":"Catching Power","type":"Water","level":1}]}]