[{"fillings":["Herbed Sausage","Apple","Apple","Banana","Banana"],"condiments":["Marmalade","Marmalade","Sweet Herba Mystica"],"mealPowers":[{"power":"Title Power","type":"Fighting","level":2},{"power":"Egg Power","level":2},{"power":"Item Drop Power","type":"Flying","level":2}]},{"fillings":["Rice"],"condiments":["Marmalade","Marmalade","Sweet Herba Mystica"],"mealPowers":[{"power":"Title Power","type":"Fighting","level":2},{"power":"Egg Power","level":2},{"power":"Item Drop Power","type":"Flying","level":1}]},{"fillings":["Pickle","Basil"],"condiments":["Whipped Cream","Bitter Herba Mystica"],"mealPowers":[{"power":"Title Power","type":"Fighting","level":2},{"power":"Item Drop Power","type":"Flying","level":2},{"power":"Egg Power","level":1}]},{"fillings":["Jalape&ntilde;o","Pineapple","Apple","Strawberry"],"condiments":["Marmalade","Spicy Herba Mystica"],"mealPowers":[{"power":"Title Power","type":"Fighting","level":2},{"power":"Item Drop Power","type":"Flying","level":2},{"power":"Egg Power","level":1}]}]