[{"fillings":["Herbed Sausage","Herbed Sausage","Herbed Sausage","Herbed Sausage","Herbed Sausage","Basil"],"condiments":["Jam","Jam","Jam","Yogurt"],"mealPowers":[{"power":"Egg Power","level":2},{"power":"Exp. Point Power","type":"Psychic","level":2},{"power":"Encounter Power","type":"Water","level":1}]},{"fillings":["Herbed Sausage","Herbed Sausage","Herbed Sausage","Herbed Sausage","Herbed Sausage"],"condiments":["Curry Powder","Vinegar","Vinegar"],"mealPowers":[{"power":"Exp. Point Power","type":"Psychic","level":2},{"power":"Encounter Power","type":"Water","level":1},{"power":"Egg Power","level":1}]},{"fillings":["Noodles","Noodles","Herbed Sausage","Herbed Sausage","Herbed Sausage"],"condiments":["Cream Cheese","Whipped Cream","Whipped Cream","Whipped Cream"],"mealPowers":[{"power":"Egg Power","level":2},{"power":"Encounter Power","type":"Water","level":1},{"power":"Exp. Point Power","type":"Psychic","level":1}]},{"fillings":["Herbed Sausage"],"condiments":["Jam","Cream Cheese","Peanut Butter","Wasabi"],"mealPowers":[{"power":"Egg Power","level":1},{"power":"Exp. Point Power","type":"Psychic","level":1},{"power":"Encounter Power","type":"Water","level":1}]}]