[{"fillings":["Fried Fillet","Potato Tortilla","Lettuce","Basil","Basil"],"condiments":["Butter","Chili Sauce","Peanut Butter","Sweet Herba Mystica"],"mealPowers":[{"power":"Title Power","type":"Grass","level":2},{"power":"Egg Power","level":2},{"power":"Raid Power","type":"Water","level":2}]},{"fillings":["Lettuce"],"condiments":["Chili Sauce","Salt","Sweet Herba Mystica"],"mealPowers":[{"power":"Title Power","type":"Grass","level":2},{"power":"Egg Power","level":2},{"power":"Raid Power","type":"Water","level":1}]},{"fillings":["Basil","Basil"],"condiments":["Chili Sauce","Curry Powder","Olive Oil","Sweet Herba Mystica"],"mealPowers":[{"power":"Title Power","type":"Grass","level":2},{"power":"Raid Power","type":"Water","level":2},{"power":"Egg Power","level":1}]},{"fillings":["Lettuce","Basil","Basil"],"condiments":["Peanut Butter","Whipped Cream","Spicy Herba Mystica"],"mealPowers":[{"power":"Title Power","type":"Grass","level":2},{"power":"Raid Power","type":"Water","level":2},{"power":"Egg Power","level":1}]}]