[{"fillings":["Green Bell Pepper","Yellow Bell Pepper"],"condiments":["Whipped Cream","Spicy Herba Mystica"],"mealPowers":[{"power":"Title Power","type":"Poison","level":2},{"power":"Raid Power","type":"Normal","level":2},{"power":"Encounter Power","type":"Electric","level":1}]},{"fillings":["Green Bell Pepper","Yellow Bell Pepper"],"condiments":["Chili Sauce","Horseradish","Sweet Herba Mystica"],"mealPowers":[{"power":"Title Power","type":"Poison","level":2},{"power":"Raid Power","type":"Normal","level":2},{"power":"Encounter Power","type":"Electric","level":1}]},{"fillings":["Potato Tortilla","Banana"],"condiments":["Horseradish","Ketchup","Salt","Salty Herba Mystica"],"mealPowers":[{"power":"Title Power","type":"Poison","level":2},{"power":"Encounter Power","type":"Electric","level":2},{"power":"Raid Power","type":"Normal","level":1}]},{"fillings":["Avocado","Green Bell Pepper","Yellow Bell Pepper","Tofu"],"condiments":["Cream Cheese","Horseradish","Marmalade","Spicy Herba Mystica"],"mealPowers":[{"power":"Title Power","type":"Poison","level":2},{"power":"Encounter Power","type":"Electric","level":2},{"power":"Raid Power","type":"Normal","level":1}]},{"fillings":["Potato Tortilla","Banana","Basil","Watercress"],"condiments":["Ketchup","Ketchup","Ketchup","Salty Herba Mystica"],"mealPowers":[{"power":"Title Power","type":"Poison","level":2},{"power":"Raid Power","type":"Normal","level":2},{"power":"Encounter Power","type":"Electric","level":1}]},{"fillings":["Hamburger","Kiwi","Onion","Yellow Bell Pepper","Tofu"],"condiments":["Jam","Horseradish","Horseradish","Sweet Herba Mystica"],"mealPowers":[{"power":"Title Power","type":"Poison","level":2},{"power":"Encounter Power","type":"Electric","level":2},{"power":"Raid Power","type":"Normal","level":1}]}]