[{"fillings":["Pickle"],"condiments":["Jam","Bitter Herba Mystica"],"mealPowers":[{"power":"Title Power","type":"Fighting","level":2},{"power":"Item Drop Power","type":"Ice","level":2},{"power":"Encounter Power","type":"Electric","level":1}]},{"fillings":["Pickle"],"condiments":["Jam","Jam","Pepper","Salty Herba Mystica"],"mealPowers":[{"power":"Title Power","type":"Fighting","level":2},{"power":"Encounter Power","type":"Electric","level":2},{"power":"Item Drop Power","type":"Ice","level":1}]},{"fillings":["Pineapple","Apple","Banana","Strawberry"],"condiments":["Jam","Marmalade","Salty Herba Mystica"],"mealPowers":[{"power":"Title Power","type":"Fighting","level":2},{"power":"Item Drop Power","type":"Ice","level":2},{"power":"Encounter Power","type":"Electric","level":1}]},{"fillings":["Klawf Stick","Onion","Yellow Bell Pepper","Pickle"],"condiments":["Curry Powder","Horseradish","Pepper","Bitter Herba Mystica"],"mealPowers":[{"power":"Title Power","type":"Fighting","level":2},{"power":"Encounter Power","type":"Electric","level":2},{"power":"Item Drop Power","type":"Ice","level":1}]},{"fillings":["Lettuce","Apple","Yellow Bell Pepper","Pickle"],"condiments":["Jam","Marmalade","Marmalade","Sour Herba Mystica"],"mealPowers":[{"power":"Title Power","type":"Fighting","level":2},{"power":"Encounter Power","type":"Electric","level":2},{"power":"Item Drop Power","type":"Ice","level":1}]},{"fillings":["Apple","Banana","Cucumber","Tomato","Strawberry"],"condiments":["Jam","Curry Powder","Marmalade","Spicy Herba Mystica"],"mealPowers":[{"power":"Title Power","type":"Fighting","level":2},{"power":"Item Drop Power","type":"Ice","level":2},{"power":"Encounter Power","type":"Electric","level":1}]},{"fillings":["Avocado","Cherry Tomatoes","Lettuce","Apple","Yellow Bell Pepper","Strawberry"],"condiments":["Jam","Marmalade","Marmalade","Spicy Herba Mystica"],"mealPowers":[{"power":"Title Power","type":"Fighting","level":2},{"power":"Encounter Power","type":"Electric","level":2},{"power":"Item Drop Power","type":"Ice","level":1}]},{"fillings":["Lettuce","Apple","Banana","Cucumber","Pickle","Watercress"],"condiments":["Jam","Marmalade","Marmalade","Sour Herba Mystica"],"mealPowers":[{"power":"Title Power","type":"Fighting","level":2},{"power":"Item Drop Power","type":"Ice","level":2},{"power":"Encounter Power","type":"Electric","level":1}]}]