[{"fillings":["Hamburger","Noodles","Klawf Stick","Bacon","Yellow Bell Pepper"],"condiments":["Curry Powder","Wasabi","Spicy Herba Mystica"],"mealPowers":[{"power":"Title Power","type":"Electric","level":2},{"power":"Encounter Power","type":"Electric","level":2},{"power":"Humungo Power","type":"Rock","level":2}]},{"fillings":["Noodles","Noodles","Noodles","Noodles","Noodles"],"condiments":["Jam","Marmalade","Salt","Salty Herba Mystica"],"mealPowers":[{"power":"Title Power","type":"Electric","level":2},{"power":"Encounter Power","type":"Electric","level":2},{"power":"Humungo Power","type":"Rock","level":2}]},{"fillings":["Noodles","Yellow Bell Pepper"],"condiments":["Cream Cheese","Mustard","Salty Herba Mystica"],"mealPowers":[{"power":"Title Power","type":"Electric","level":2},{"power":"Encounter Power","type":"Electric","level":2},{"power":"Humungo Power","type":"Rock","level":1}]},{"fillings":["Jalape&ntilde;o","Yellow Bell Pepper","Yellow Bell Pepper"],"condiments":["Curry Powder","Curry Powder","Curry Powder","Spicy Herba Mystica"],"mealPowers":[{"power":"Title Power","type":"Electric","level":2},{"power":"Encounter Power","type":"Electric","level":2},{"power":"Humungo Power","type":"Rock","level":1}]}]