[{"fillings":["Hamburger","Hamburger","Noodles","Tofu","Tofu"],"condiments":["Butter","Wasabi","Spicy Herba Mystica"],"mealPowers":[{"power":"Title Power","type":"Normal","level":2},{"power":"Raid Power","type":"Normal","level":2},{"power":"Encounter Power","type":"Electric","level":2}]},{"fillings":["Hamburger","Noodles","Avocado","Tofu","Tofu"],"condiments":["Pepper","Wasabi","Sweet Herba Mystica"],"mealPowers":[{"power":"Title Power","type":"Normal","level":2},{"power":"Raid Power","type":"Normal","level":2},{"power":"Encounter Power","type":"Electric","level":2}]},{"fillings":["Fried Fillet","Fried Fillet","Potato Tortilla","Potato Tortilla","Chorizo"],"condiments":["Butter","Mayonnaise","Salt","Salty Herba Mystica"],"mealPowers":[{"power":"Title Power","type":"Normal","level":2},{"power":"Raid Power","type":"Normal","level":2},{"power":"Encounter Power","type":"Electric","level":2}]},{"fillings":["Chorizo"],"condiments":["Jam","Horseradish","Horseradish","Spicy Herba Mystica"],"mealPowers":[{"power":"Title Power","type":"Normal","level":2},{"power":"Raid Power","type":"Normal","level":2},{"power":"Encounter Power","type":"Electric","level":1}]},{"fillings":["Chorizo"],"condiments":["Jam","Horseradish","Horseradish","Sweet Herba Mystica"],"mealPowers":[{"power":"Title Power","type":"Normal","level":2},{"power":"Raid Power","type":"Normal","level":2},{"power":"Encounter Power","type":"Electric","level":1}]},{"fillings":["Fried Fillet","Cheese","Basil"],"condiments":["Butter","Mayonnaise","Mayonnaise","Salty Herba Mystica"],"mealPowers":[{"power":"Title Power","type":"Normal","level":2},{"power":"Raid Power","type":"Normal","level":2},{"power":"Encounter Power","type":"Electric","level":1}]}]