[{"fillings":["Bacon","Red Bell Pepper"],"condiments":["Ketchup","Marmalade","Salty Herba Mystica"],"mealPowers":[{"power":"Title Power","type":"Rock","level":2},{"power":"Exp. Point Power","type":"Poison","level":2},{"power":"Encounter Power","type":"Fire","level":1}]},{"fillings":["Bacon","Red Bell Pepper"],"condiments":["Butter","Ketchup","Marmalade","Bitter Herba Mystica"],"mealPowers":[{"power":"Title Power","type":"Rock","level":2},{"power":"Exp. Point Power","type":"Poison","level":2},{"power":"Encounter Power","type":"Fire","level":1}]},{"fillings":["Avocado","Bacon","Green Bell Pepper","Red Bell Pepper","Smoked Fillet"],"condiments":["Horseradish","Mustard","Bitter Herba Mystica"],"mealPowers":[{"power":"Title Power","type":"Rock","level":2},{"power":"Encounter Power","type":"Fire","level":2},{"power":"Exp. Point Power","type":"Poison","level":1}]},{"fillings":["Avocado","Klawf Stick","Bacon","Green Bell Pepper","Red Bell Pepper"],"condiments":["Horseradish","Mustard","Salty Herba Mystica"],"mealPowers":[{"power":"Title Power","type":"Rock","level":2},{"power":"Encounter Power","type":"Fire","level":2},{"power":"Exp. Point Power","type":"Poison","level":1}]}]