[{"fillings":["Noodles","Rice"],"condiments":["Pepper","Spicy Herba Mystica"],"mealPowers":[{"power":"Title Power","type":"Ice","level":2},{"power":"Humungo Power","type":"Ice","level":2},{"power":"Encounter Power","type":"Fighting","level":2}]},{"fillings":["Noodles","Noodles","Rice","Rice","Klawf Stick"],"condiments":["Jam","Marmalade","Salt","Sour Herba Mystica"],"mealPowers":[{"power":"Title Power","type":"Ice","level":2},{"power":"Humungo Power","type":"Ice","level":2},{"power":"Encounter Power","type":"Fighting","level":2}]}]