[{"fillings":["Pickle","Tomato"],"condiments":["Chili Sauce","Wasabi","Yogurt","Sour Herba Mystica"],"mealPowers":[{"power":"Title Power","type":"Fairy","level":2},{"power":"Teensy Power","type":"Dark","level":2},{"power":"Encounter Power","type":"Fighting","level":1}]},{"fillings":["Hamburger","Pickle","Tomato","Smoked Fillet"],"condiments":["Olive Oil","Vinegar","Wasabi","Sour Herba Mystica"],"mealPowers":[{"power":"Title Power","type":"Fairy","level":2},{"power":"Encounter Power","type":"Fighting","level":2},{"power":"Teensy Power","type":"Dark","level":1}]}]