[{"fillings":["Lettuce","Tomato"],"condiments":["Butter","Mustard","Spicy Herba Mystica"],"mealPowers":[{"power":"Title Power","type":"Grass","level":2},{"power":"Raid Power","type":"Ground","level":2},{"power":"Encounter Power","type":"Fairy","level":1}]},{"fillings":["Lettuce","Tomato"],"condiments":["Chili Sauce","Mustard","Sweet Herba Mystica"],"mealPowers":[{"power":"Title Power","type":"Grass","level":2},{"power":"Raid Power","type":"Ground","level":2},{"power":"Encounter Power","type":"Fairy","level":1}]},{"fillings":["Lettuce","Ham"],"condiments":["Chili Sauce","Vinegar","Yogurt","Salty Herba Mystica"],"mealPowers":[{"power":"Title Power","type":"Grass","level":2},{"power":"Encounter Power","type":"Fairy","level":2},{"power":"Raid Power","type":"Ground","level":1}]},{"fillings":["Lettuce","Ham","Tomato"],"condiments":["Curry Powder","Curry Powder","Curry Powder","Sweet Herba Mystica"],"mealPowers":[{"power":"Title Power","type":"Grass","level":2},{"power":"Encounter Power","type":"Fairy","level":2},{"power":"Raid Power","type":"Ground","level":1}]},{"fillings":["Lettuce","Cucumber","Ham","Tomato"],"condiments":["Horseradish","Olive Oil","Wasabi","Spicy Herba Mystica"],"mealPowers":[{"power":"Title Power","type":"Grass","level":2},{"power":"Encounter Power","type":"Fairy","level":2},{"power":"Raid Power","type":"Ground","level":1}]}]