[{"fillings":["Lettuce","Cucumber","Basil"],"condiments":["Salty Herba Mystica"],"mealPowers":[{"power":"Title Power","type":"Water","level":2},{"power":"Exp. Point Power","type":"Fire","level":2},{"power":"Encounter Power","type":"Grass","level":1}]},{"fillings":["Lettuce","Cucumber","Basil"],"condiments":["Butter","Bitter Herba Mystica"],"mealPowers":[{"power":"Title Power","type":"Water","level":2},{"power":"Exp. Point Power","type":"Fire","level":2},{"power":"Encounter Power","type":"Grass","level":1}]},{"fillings":["Bacon","Lettuce","Cucumber","Red Bell Pepper"],"condiments":["Cream Cheese","Cream Cheese","Curry Powder","Bitter Herba Mystica"],"mealPowers":[{"power":"Title Power","type":"Water","level":2},{"power":"Encounter Power","type":"Grass","level":2},{"power":"Exp. Point Power","type":"Fire","level":1}]},{"fillings":["Bacon","Lettuce","Cucumber","Red Bell Pepper"],"condiments":["Jam","Cream Cheese","Curry Powder","Salty Herba Mystica"],"mealPowers":[{"power":"Title Power","type":"Water","level":2},{"power":"Encounter Power","type":"Grass","level":2},{"power":"Exp. Point Power","type":"Fire","level":1}]}]