[{"fillings":["Klawf Stick","Pickle","Smoked Fillet"],"condiments":["Bitter Herba Mystica"],"mealPowers":[{"power":"Title Power","type":"Fighting","level":2},{"power":"Exp. Point Power","type":"Dark","level":2},{"power":"Encounter Power","type":"Ice","level":1}]},{"fillings":["Klawf Stick","Pickle","Smoked Fillet"],"condiments":["Marmalade","Salty Herba Mystica"],"mealPowers":[{"power":"Title Power","type":"Fighting","level":2},{"power":"Exp. Point Power","type":"Dark","level":2},{"power":"Encounter Power","type":"Ice","level":1}]},{"fillings":["Hamburger","Klawf Stick","Prosciutto","Ham","Pickle","Smoked Fillet"],"condiments":["Marmalade","Wasabi","Yogurt","Bitter Herba Mystica"],"mealPowers":[{"power":"Title Power","type":"Fighting","level":2},{"power":"Encounter Power","type":"Ice","level":2},{"power":"Exp. Point Power","type":"Dark","level":1}]},{"fillings":["Klawf Stick","Lettuce","Red Bell Pepper","Pickle","Smoked Fillet","Watercress"],"condiments":["Marmalade","Wasabi","Yogurt","Salty Herba Mystica"],"mealPowers":[{"power":"Title Power","type":"Fighting","level":2},{"power":"Encounter Power","type":"Ice","level":2},{"power":"Exp. Point Power","type":"Dark","level":1}]}]