[{"fillings":["Rice","Rice","Rice","Rice","Rice","Egg"],"condiments":["Jam","Mayonnaise","Salt"],"mealPowers":[{"power":"Humungo Power","type":"Flying","level":2},{"power":"Encounter Power","type":"Normal","level":1},{"power":"Teensy Power","type":"Grass","level":1}]},{"fillings":["Rice","Rice","Rice","Rice","Egg","Egg"],"condiments":["Curry Powder","Mayonnaise","Mayonnaise"],"mealPowers":[{"power":"Teensy Power","type":"Grass","level":2},{"power":"Encounter Power","type":"Normal","level":1},{"power":"Humungo Power","type":"Flying","level":1}]},{"fillings":["Prosciutto"],"condiments":["Chili Sauce","Horseradish","Horseradish","Olive Oil"],"mealPowers":[{"power":"Humungo Power","type":"Flying","level":1},{"power":"Encounter Power","type":"Normal","level":1},{"power":"Teensy Power","type":"Grass","level":1}]}]