[{"fillings":["Rice","Rice","Rice","Rice","Rice","Rice"],"condiments":["Cream Cheese","Ketchup","Ketchup","Ketchup"],"mealPowers":[{"power":"Humungo Power","type":"Flying","level":2},{"power":"Encounter Power","type":"Normal","level":2},{"power":"Teensy Power","type":"Water","level":1}]},{"fillings":["Rice"],"condiments":["Cream Cheese","Horseradish","Ketchup","Wasabi"],"mealPowers":[{"power":"Humungo Power","type":"Flying","level":1},{"power":"Encounter Power","type":"Normal","level":1},{"power":"Teensy Power","type":"Water","level":1}]}]