[{"fillings":["Avocado","Cucumber"],"condiments":["Butter","Mayonnaise","Salty Herba Mystica"],"mealPowers":[{"power":"Title Power","type":"Water","level":2},{"power":"Encounter Power","type":"Normal","level":2},{"power":"Raid Power","type":"Dragon","level":1}]},{"fillings":["Cucumber","Tofu"],"condiments":["Chili Sauce","Pepper","Vinegar","Sweet Herba Mystica"],"mealPowers":[{"power":"Title Power","type":"Water","level":2},{"power":"Raid Power","type":"Dragon","level":2},{"power":"Encounter Power","type":"Normal","level":1}]},{"fillings":["Avocado","Cucumber","Tofu"],"condiments":["Chili Sauce","Spicy Herba Mystica"],"mealPowers":[{"power":"Title Power","type":"Water","level":2},{"power":"Raid Power","type":"Dragon","level":2},{"power":"Encounter Power","type":"Normal","level":1}]},{"fillings":["Avocado","Cucumber","Tofu"],"condiments":["Curry Powder","Curry Powder","Wasabi","Spicy Herba Mystica"],"mealPowers":[{"power":"Title Power","type":"Water","level":2},{"power":"Encounter Power","type":"Normal","level":2},{"power":"Raid Power","type":"Dragon","level":1}]},{"fillings":["Avocado","Cucumber","Tofu"],"condiments":["Curry Powder","Curry Powder","Wasabi","Sweet Herba Mystica"],"mealPowers":[{"power":"Title Power","type":"Water","level":2},{"power":"Encounter Power","type":"Normal","level":2},{"power":"Raid Power","type":"Dragon","level":1}]}]