[{"fillings":["Onion","Yellow Bell Pepper"],"condiments":["Ketchup","Spicy Herba Mystica"],"mealPowers":[{"power":"Title Power","type":"Electric","level":2},{"power":"Humungo Power","type":"Flying","level":2},{"power":"Encounter Power","type":"Psychic","level":1}]},{"fillings":["Avocado","Prosciutto","Onion","Yellow Bell Pepper","Tomato"],"condiments":["Jam","Mayonnaise","Spicy Herba Mystica"],"mealPowers":[{"power":"Title Power","type":"Electric","level":2},{"power":"Encounter Power","type":"Psychic","level":2},{"power":"Humungo Power","type":"Flying","level":1}]}]