[{"fillings":["Hamburger","Onion"],"condiments":["Cream Cheese","Vinegar","Yogurt","Spicy Herba Mystica"],"mealPowers":[{"power":"Title Power","type":"Steel","level":2},{"power":"Humungo Power","type":"Fairy","level":2},{"power":"Encounter Power","type":"Psychic","level":1}]},{"fillings":["Hamburger","Bacon","Ham","Onion","Tomato"],"condiments":["Cream Cheese","Wasabi","Yogurt","Spicy Herba Mystica"],"mealPowers":[{"power":"Title Power","type":"Steel","level":2},{"power":"Encounter Power","type":"Psychic","level":2},{"power":"Humungo Power","type":"Fairy","level":1}]}]