[{"fillings":["Bacon"],"condiments":["Salt","Yogurt","Salty Herba Mystica"],"mealPowers":[{"power":"Title Power","type":"Rock","level":2},{"power":"Encounter Power","type":"Psychic","level":2},{"power":"Raid Power","type":"Electric","level":1}]},{"fillings":["Bacon","Onion"],"condiments":["Jam","Spicy Herba Mystica"],"mealPowers":[{"power":"Title Power","type":"Rock","level":2},{"power":"Raid Power","type":"Electric","level":2},{"power":"Encounter Power","type":"Psychic","level":1}]},{"fillings":["Bacon","Onion"],"condiments":["Jam","Curry Powder","Sweet Herba Mystica"],"mealPowers":[{"power":"Title Power","type":"Rock","level":2},{"power":"Raid Power","type":"Electric","level":2},{"power":"Encounter Power","type":"Psychic","level":1}]},{"fillings":["Bacon","Onion","Yellow Bell Pepper"],"condiments":["Horseradish","Horseradish","Horseradish","Spicy Herba Mystica"],"mealPowers":[{"power":"Title Power","type":"Rock","level":2},{"power":"Encounter Power","type":"Psychic","level":2},{"power":"Raid Power","type":"Electric","level":1}]},{"fillings":["Bacon","Onion","Yellow Bell Pepper"],"condiments":["Curry Powder","Curry Powder","Curry Powder","Sweet Herba Mystica"],"mealPowers":[{"power":"Title Power","type":"Rock","level":2},{"power":"Encounter Power","type":"Psychic","level":2},{"power":"Raid Power","type":"Electric","level":1}]}]