[{"fillings":["Ham"],"condiments":["Vinegar","Spicy Herba Mystica"],"mealPowers":[{"power":"Title Power","type":"Ground","level":2},{"power":"Humungo Power","type":"Dragon","level":2},{"power":"Encounter Power","type":"Psychic","level":1}]},{"fillings":["Avocado","Ham","Onion","Smoked Fillet"],"condiments":["Curry Powder","Horseradish","Pepper","Spicy Herba Mystica"],"mealPowers":[{"power":"Title Power","type":"Ground","level":2},{"power":"Encounter Power","type":"Psychic","level":2},{"power":"Humungo Power","type":"Dragon","level":1}]}]