[{"fillings":["Cucumber","Green Bell Pepper"],"condiments":["Peanut Butter","Bitter Herba Mystica"],"mealPowers":[{"power":"Title Power","type":"Poison","level":2},{"power":"Item Drop Power","type":"Steel","level":2},{"power":"Encounter Power","type":"Water","level":1}]},{"fillings":["Hamburger","Cucumber","Kiwi"],"condiments":["Cream Cheese","Horseradish","Salty Herba Mystica"],"mealPowers":[{"power":"Title Power","type":"Poison","level":2},{"power":"Encounter Power","type":"Water","level":2},{"power":"Item Drop Power","type":"Steel","level":1}]},{"fillings":["Hamburger","Avocado","Cucumber","Green Bell Pepper"],"condiments":["Curry Powder","Horseradish","Bitter Herba Mystica"],"mealPowers":[{"power":"Title Power","type":"Poison","level":2},{"power":"Encounter Power","type":"Water","level":2},{"power":"Item Drop Power","type":"Steel","level":1}]},{"fillings":["Hamburger","Lettuce","Cucumber","Kiwi"],"condiments":["Cream Cheese","Marmalade","Marmalade","Sour Herba Mystica"],"mealPowers":[{"power":"Title Power","type":"Poison","level":2},{"power":"Encounter Power","type":"Water","level":2},{"power":"Item Drop Power","type":"Steel","level":1}]},{"fillings":["Pineapple","Apple","Kiwi","Basil"],"condiments":["Cream Cheese","Marmalade","Marmalade","Salty Herba Mystica"],"mealPowers":[{"power":"Title Power","type":"Poison","level":2},{"power":"Item Drop Power","type":"Steel","level":2},{"power":"Encounter Power","type":"Water","level":1}]},{"fillings":["Cherry Tomatoes","Bacon","Pineapple","Apple","Kiwi"],"condiments":["Chili Sauce","Curry Powder","Marmalade","Spicy Herba Mystica"],"mealPowers":[{"power":"Title Power","type":"Poison","level":2},{"power":"Item Drop Power","type":"Steel","level":2},{"power":"Encounter Power","type":"Water","level":1}]},{"fillings":["Hamburger","Lettuce","Pineapple","Kiwi","Yellow Bell Pepper"],"condiments":["Cream Cheese","Marmalade","Marmalade","Sour Herba Mystica"],"mealPowers":[{"power":"Title Power","type":"Poison","level":2},{"power":"Item Drop Power","type":"Steel","level":2},{"power":"Encounter Power","type":"Water","level":1}]},{"fillings":["Avocado","Cherry Tomatoes","Lettuce","Pineapple","Apple","Green Bell Pepper"],"condiments":["Cream Cheese","Marmalade","Marmalade","Spicy Herba Mystica"],"mealPowers":[{"power":"Title Power","type":"Poison","level":2},{"power":"Encounter Power","type":"Water","level":2},{"power":"Item Drop Power","type":"Steel","level":1}]}]