[{"fillings":["Yellow Bell Pepper","Tofu"],"condiments":["Chili Sauce","Salt","Salty Herba Mystica"],"mealPowers":[{"power":"Title Power","type":"Electric","level":2},{"power":"Encounter Power","type":"Water","level":2},{"power":"Raid Power","type":"Normal","level":1}]},{"fillings":["Cucumber","Yellow Bell Pepper"],"condiments":["Jam","Whipped Cream","Spicy Herba Mystica"],"mealPowers":[{"power":"Title Power","type":"Electric","level":2},{"power":"Raid Power","type":"Normal","level":2},{"power":"Encounter Power","type":"Water","level":1}]},{"fillings":["Cucumber","Yellow Bell Pepper"],"condiments":["Horseradish","Wasabi","Sweet Herba Mystica"],"mealPowers":[{"power":"Title Power","type":"Electric","level":2},{"power":"Raid Power","type":"Normal","level":2},{"power":"Encounter Power","type":"Water","level":1}]},{"fillings":["Cucumber","Yellow Bell Pepper","Tofu"],"condiments":["Horseradish","Wasabi","Wasabi","Spicy Herba Mystica"],"mealPowers":[{"power":"Title Power","type":"Electric","level":2},{"power":"Encounter Power","type":"Water","level":2},{"power":"Raid Power","type":"Normal","level":1}]},{"fillings":["Cucumber","Yellow Bell Pepper","Tofu"],"condiments":["Horseradish","Wasabi","Wasabi","Sweet Herba Mystica"],"mealPowers":[{"power":"Title Power","type":"Electric","level":2},{"power":"Encounter Power","type":"Water","level":2},{"power":"Raid Power","type":"Normal","level":1}]}]