[{"fillings":["Bacon","Basil"],"condiments":["Peanut Butter","Salt","Bitter Herba Mystica"],"mealPowers":[{"power":"Title Power","type":"Rock","level":2},{"power":"Exp. Point Power","type":"Electric","level":2},{"power":"Raid Power","type":"Fire","level":1}]},{"fillings":["Bacon","Basil"],"condiments":["Peanut Butter","Salt","Salty Herba Mystica"],"mealPowers":[{"power":"Title Power","type":"Rock","level":2},{"power":"Exp. Point Power","type":"Electric","level":2},{"power":"Raid Power","type":"Fire","level":1}]},{"fillings":["Potato Tortilla","Banana","Basil"],"condiments":["Horseradish","Mustard","Mustard","Sweet Herba Mystica"],"mealPowers":[{"power":"Title Power","type":"Rock","level":2},{"power":"Raid Power","type":"Fire","level":2},{"power":"Exp. Point Power","type":"Electric","level":1}]}]