[{"fillings":["Onion","Basil"],"condiments":["Salt","Bitter Herba Mystica"],"mealPowers":[{"power":"Title Power","type":"Psychic","level":2},{"power":"Exp. Point Power","type":"Fire","level":2},{"power":"Raid Power","type":"Electric","level":1}]},{"fillings":["Onion","Basil"],"condiments":["Salt","Salty Herba Mystica"],"mealPowers":[{"power":"Title Power","type":"Psychic","level":2},{"power":"Exp. Point Power","type":"Fire","level":2},{"power":"Raid Power","type":"Electric","level":1}]},{"fillings":["Onion","Basil"],"condiments":["Jam","Peanut Butter","Peanut Butter","Spicy Herba Mystica"],"mealPowers":[{"power":"Title Power","type":"Psychic","level":2},{"power":"Raid Power","type":"Electric","level":2},{"power":"Exp. Point Power","type":"Fire","level":1}]},{"fillings":["Onion","Basil","Basil"],"condiments":["Mustard","Peanut Butter","Wasabi","Sweet Herba Mystica"],"mealPowers":[{"power":"Title Power","type":"Psychic","level":2},{"power":"Raid Power","type":"Electric","level":2},{"power":"Exp. Point Power","type":"Fire","level":1}]}]