[{"fillings":["Hamburger","Green Bell Pepper"],"condiments":["Butter","Chili Sauce","Chili Sauce","Bitter Herba Mystica"],"mealPowers":[{"power":"Title Power","type":"Poison","level":2},{"power":"Exp. Point Power","type":"Water","level":2},{"power":"Raid Power","type":"Steel","level":1}]},{"fillings":["Hamburger","Green Bell Pepper"],"condiments":["Chili Sauce","Pepper","Salt","Salty Herba Mystica"],"mealPowers":[{"power":"Title Power","type":"Poison","level":2},{"power":"Exp. Point Power","type":"Water","level":2},{"power":"Raid Power","type":"Steel","level":1}]},{"fillings":["Green Bell Pepper","Basil"],"condiments":["Cream Cheese","Peanut Butter","Yogurt","Spicy Herba Mystica"],"mealPowers":[{"power":"Title Power","type":"Poison","level":2},{"power":"Raid Power","type":"Steel","level":2},{"power":"Exp. Point Power","type":"Water","level":1}]},{"fillings":["Hamburger","Cucumber","Kiwi","Watercress"],"condiments":["Chili Sauce","Chili Sauce","Chili Sauce","Sweet Herba Mystica"],"mealPowers":[{"power":"Title Power","type":"Poison","level":2},{"power":"Raid Power","type":"Steel","level":2},{"power":"Exp. Point Power","type":"Water","level":1}]}]