[{"fillings":["Potato Tortilla","Potato Tortilla","Potato Tortilla","Potato Tortilla"],"condiments":["Mayonnaise","Salt","Salt","Spicy Herba Mystica"],"mealPowers":[{"power":"Title Power","type":"Psychic","level":2},{"power":"Raid Power","type":"Psychic","level":2},{"power":"Humungo Power","type":"Poison","level":2}]},{"fillings":["Noodles","Noodles","Noodles","Noodles","Rice"],"condiments":["Chili Sauce","Pepper","Vinegar","Sweet Herba Mystica"],"mealPowers":[{"power":"Title Power","type":"Psychic","level":2},{"power":"Raid Power","type":"Psychic","level":2},{"power":"Humungo Power","type":"Poison","level":2}]},{"fillings":["Noodles","Noodles"],"condiments":["Chili Sauce","Pepper","Vinegar","Sweet Herba Mystica"],"mealPowers":[{"power":"Title Power","type":"Psychic","level":2},{"power":"Raid Power","type":"Psychic","level":2},{"power":"Humungo Power","type":"Poison","level":1}]},{"fillings":["Noodles","Noodles","Strawberry"],"condiments":["Pepper","Spicy Herba Mystica"],"mealPowers":[{"power":"Title Power","type":"Psychic","level":2},{"power":"Raid Power","type":"Psychic","level":2},{"power":"Humungo Power","type":"Poison","level":1}]}]