[{"fillings":["Jalape&ntilde;o","Pineapple","Strawberry"],"condiments":["Mustard","Salt","Spicy Herba Mystica"],"mealPowers":[{"power":"Title Power","type":"Ground","level":2},{"power":"Item Drop Power","type":"Psychic","level":2},{"power":"Humungo Power","type":"Rock","level":1}]},{"fillings":["Bacon","Pineapple","Strawberry"],"condiments":["Mustard","Mustard","Vinegar","Spicy Herba Mystica"],"mealPowers":[{"power":"Title Power","type":"Ground","level":2},{"power":"Humungo Power","type":"Rock","level":2},{"power":"Item Drop Power","type":"Psychic","level":1}]}]