[{"fillings":["Noodles","Jalape&ntilde;o"],"condiments":["Horseradish","Horseradish","Spicy Herba Mystica"],"mealPowers":[{"power":"Title Power","type":"Rock","level":2},{"power":"Raid Power","type":"Rock","level":2},{"power":"Teensy Power","type":"Ground","level":2}]},{"fillings":["Noodles","Jalape&ntilde;o"],"condiments":["Curry Powder","Curry Powder","Sweet Herba Mystica"],"mealPowers":[{"power":"Title Power","type":"Rock","level":2},{"power":"Raid Power","type":"Rock","level":2},{"power":"Teensy Power","type":"Ground","level":2}]},{"fillings":["Fried Fillet","Potato Tortilla","Potato Tortilla","Ham","Watercress"],"condiments":["Ketchup","Mustard","Mustard","Sour Herba Mystica"],"mealPowers":[{"power":"Title Power","type":"Rock","level":2},{"power":"Raid Power","type":"Rock","level":2},{"power":"Teensy Power","type":"Ground","level":2}]}]